<?xml version="1.0" encoding="UTF-8"?>
<!-- 
      - This file is generated by lexicon-skeleton.xsl to set up
          accusativity/ergativity parameter for IV and TV primary families
          and control primary families.
      - Modify it to set up a particular lexicon
          NB: pre-CCG categories of lexicon-skeleton.xml are mapped to
              CCG categories in this file. From now on, it's all CCG
      - After modifying preset families, add your own families as needed.
          Then, you can use the build facility of openCCG to build
          the lexicon.xml, morph.xml and rules.xml files needed by the system.
          If you hand-code the entries, families and members, you do not need 
          to use the build facility.
  -->
<!-- Additional families by Cem Bozsahin , 6/2003 -->
<!--

      *** Families derived from language parameters ***

   Includes primary entries for IV, TV, TV-control1, TV-control2, IV-control1
   
  -->
<ccg-lexicon xmlns:xsi="http://www.w3.org/2001/XMLSchema-instance" xsi:noNamespaceSchemaLocation="../lexicon.xsd" name="Basque">
  <family closed="true" pos="V" name="unergative">
    <entry name="primary">
      <complexcat>
        <atomcat type="s">
          <fs id="0">
            <feat attr="index">
              <lf>
                <nomvar name="E"/>
              </lf>
            </feat>
          </fs>
        </atomcat>
        <slash dir="\"/>
        <atomcat type="np">
          <fs id="1">
            <feat attr="case" val="s-case"/>
            <feat attr="index">
              <lf>
                <nomvar name="X1"/>
              </lf>
            </feat>
          </fs>
        </atomcat>
        <lf>
          <satop nomvar="E">
            <prop name="[*DEFAULT*]"/>
            <diamond mode="Arg1">
              <nomvar name="X1"/>
            </diamond>
            <diamond mode="Arg2">
              <nom name="one"/>
            </diamond>
          </satop>
        </lf>
      </complexcat>
    </entry>
    <member stem="joan" pred="go"/>
    <member stem="usteltzen" pred="rot"/>
  </family>
  <family closed="true" pos="V" name="unaccusative">
    <entry name="primary">
      <complexcat>
        <atomcat type="s">
          <fs id="0">
            <feat attr="index">
              <lf>
                <nomvar name="E"/>
              </lf>
            </feat>
          </fs>
        </atomcat>
        <slash dir="\"/>
        <atomcat type="np">
          <fs id="1">
            <feat attr="case" val="s-case"/>
            <feat attr="index">
              <lf>
                <nomvar name="X1"/>
              </lf>
            </feat>
          </fs>
        </atomcat>
        <lf>
          <satop nomvar="E">
            <prop name="[*DEFAULT*]"/>
            <diamond mode="Arg2">
              <nomvar name="X1"/>
            </diamond>
            <diamond mode="Arg1">
              <nom name="one"/>
            </diamond>
          </satop>
        </lf>
      </complexcat>
    </entry>
  </family>
  <family closed="true" pos="V" name="TV">
    <entry name="primary">
      <complexcat>
        <atomcat type="s">
          <fs id="0">
            <feat attr="index">
              <lf>
                <nomvar name="E"/>
              </lf>
            </feat>
          </fs>
        </atomcat>
        <setarg>
          <slash dir="\"/>
          <atomcat type="np">
            <fs id="1">
              <feat attr="case" val="a-case"/>
              <feat attr="index">
                <lf>
                  <nomvar name="X1:1"/>
                </lf>
              </feat>
            </fs>
          </atomcat>
          <slash dir="\"/>
          <atomcat type="np">
            <fs id="2">
              <feat attr="case" val="p-case"/>
              <feat attr="index">
                <lf>
                  <nomvar name="X2:2"/>
                </lf>
              </feat>
            </fs>
          </atomcat>
        </setarg>
        <lf>
          <satop nomvar="E">
            <prop name="[*DEFAULT*]"/>
            <diamond mode="Arg1">
              <nomvar name="X1:1"/>
            </diamond>
            <diamond mode="Arg2">
              <nomvar name="X2:2"/>
            </diamond>
          </satop>
        </lf>
      </complexcat>
    </entry>
    <member stem="egin" pred="do"/>
    <member stem="utzi" pred="leave"/>
    <member stem="egosten" pred="cook"/>
    <member stem="jaten" pred="eat"/>
    <member stem="ikusi" pred="see"/>
    <member stem="nahi" pred="want"/>
  </family>
  <family closed="true" pos="V" name="TV-control2">
    <entry name="primary">
      <complexcat>
        <atomcat type="s">
          <fs id="0">
            <feat attr="index">
              <lf>
                <nomvar name="E"/>
              </lf>
            </feat>
          </fs>
        </atomcat>
        <setarg>
          <slash dir="\"/>
          <atomcat type="np">
            <fs id="1">
              <feat attr="case" val="a-case"/>
              <feat attr="index">
                <lf>
                  <nomvar name="X1"/>
                </lf>
              </feat>
            </fs>
          </atomcat>
          <slash dir="\"/>
          <complexcat>
            <!--NB: Word order and directionality of embedded clause's |(S|NP) 
type is an 'educated guess' from the syntactic type of TV. Change them
accordingly 
  -->
            <atomcat type="s">
              <fs id="3">
                <feat val="non-fin" attr="vform"/>
                <feat attr="index">
                  <lf>
                    <nomvar name="E2"/>
                  </lf>
                </feat>
              </fs>
            </atomcat>
            <slash dir="|"/>
            <atomcat type="np">
              <fs id="4">
                <feat attr="index">
                  <lf>
                    <nomvar name="X2"/>
                    <!--NB: Index is same as Arg2's 
  -->
                  </lf>
                </feat>
              </fs>
            </atomcat>
          </complexcat>
          <slash dir="\"/>
          <atomcat type="np">
            <fs id="2">
              <feat attr="case" val="p-case"/>
              <feat attr="index">
                <lf>
                  <nomvar name="X2"/>
                </lf>
              </feat>
            </fs>
          </atomcat>
        </setarg>
        <lf>
          <satop nomvar="E">
            <prop name="[*DEFAULT*]"/>
            <diamond mode="Arg1">
              <nomvar name="X1"/>
            </diamond>
            <diamond mode="Arg2">
              <nomvar name="X2"/>
            </diamond>
            <diamond mode="Arg3">
              <nomvar name="E2"/>
              <!--NB: Argument is the PAS of the embedded S|NP  (cf. E2 above)
-->
            </diamond>
          </satop>
          <satop nomvar="E2">
            <!-- semantic subj control w/o case -->
            <diamond mode="Arg1">
              <nomvar name="X2"/>
            </diamond>
          </satop>
        </lf>
      </complexcat>
    </entry>
  </family>
  <family closed="true" pos="V" name="TV-control1">
    <entry name="primary">
      <complexcat>
        <atomcat type="s">
          <fs id="0">
            <feat attr="index">
              <lf>
                <nomvar name="E"/>
              </lf>
            </feat>
          </fs>
        </atomcat>
        <setarg>
          <slash dir="\"/>
          <atomcat type="np">
            <fs id="1">
              <feat attr="case" val="a-case"/>
              <feat attr="index">
                <lf>
                  <nomvar name="X1"/>
                </lf>
              </feat>
            </fs>
          </atomcat>
          <slash dir="\"/>
          <complexcat>
            <!--NB: Word order and directionality of embedded clause's 
|(S|NP) type is an 'educated guess' from the syntactic type of TV. 
Change them accordingly.
  -->
            <atomcat type="s">
              <fs id="3">
                <feat val="non-fin" attr="vform"/>
                <feat attr="index">
                  <lf>
                    <nomvar name="E2"/>
                  </lf>
                </feat>
              </fs>
            </atomcat>
            <slash dir="|"/>
            <atomcat type="np">
              <fs id="4">
                <feat attr="index">
                  <lf>
                    <nomvar name="X1"/>
                    <!--NB: Index is same as Arg1's 
  -->
                  </lf>
                </feat>
              </fs>
            </atomcat>
          </complexcat>
          <slash dir="\"/>
          <atomcat type="np">
            <fs id="2">
              <feat attr="case" val="p-case"/>
              <feat attr="index">
                <lf>
                  <nomvar name="X2"/>
                </lf>
              </feat>
            </fs>
          </atomcat>
        </setarg>
        <lf>
          <satop nomvar="E">
            <prop name="[*DEFAULT*]"/>
            <diamond mode="Arg1">
              <nomvar name="X1"/>
            </diamond>
            <diamond mode="Arg2">
              <nomvar name="X2"/>
            </diamond>
            <diamond mode="Arg3">
              <nomvar name="E2"/>
              <!--NB: Argument is the PAS of the embedded S|NP  (cf. E2 above)
-->
            </diamond>
          </satop>
          <satop nomvar="E2">
            <!-- sem. subj control -->
            <diamond mode="Arg1">
              <nomvar name="X1"/>
            </diamond>
          </satop>
        </lf>
      </complexcat>
    </entry>
  </family>
  <family closed="true" pos="V" name="IV-control1">
    <entry name="primary">
      <complexcat>
        <atomcat type="s">
          <fs id="0">
            <feat attr="index">
              <lf>
                <nomvar name="E"/>
              </lf>
            </feat>
          </fs>
        </atomcat>
        <setarg>
          <slash dir="\"/>
          <atomcat type="np">
            <fs id="1">
              <feat attr="case" val="a-case"/>
              <feat attr="index">
                <lf>
                  <nomvar name="X1"/>
                </lf>
              </feat>
            </fs>
          </atomcat>
          <slash dir="|"/>
          <complexcat>
            <!--NB: Word order and directionality of embedded clause's 
|(S|NP) type is an 'educated guess' from the syntactic type of TV. 
Change them accordingly.
  -->
            <atomcat type="s">
              <fs id="3">
                <feat val="non-fin" attr="vform"/>
                <feat attr="index">
                  <lf>
                    <nomvar name="E2"/>
                  </lf>
                </feat>
              </fs>
            </atomcat>
            <slash dir="\"/>
            <atomcat type="np">
              <fs id="4">
                <feat attr="index">
                  <lf>
                    <nomvar name="X1"/>
                    <!--NB: Index is same as Arg1's 
  -->
                  </lf>
                </feat>
              </fs>
            </atomcat>
          </complexcat>
        </setarg>
        <lf>
          <satop nomvar="E">
            <prop name="[*DEFAULT*]"/>
            <diamond mode="Arg1">
              <nomvar name="X1"/>
            </diamond>
            <diamond mode="Arg2">
              <nomvar name="E2"/>
              <!--NB: Argument is the PAS of the embedded S|NP  (cf. E2 above)
-->
            </diamond>
          </satop>
          <satop nomvar="E2">
            <!-- sem. subj control -->
            <diamond mode="Arg1">
              <nomvar name="X1"/>
            </diamond>
          </satop>
        </lf>
      </complexcat>
    </entry>
    <member stem="nahi" pred="want"/>
  </family>
  <!--

    *** End of derived families ***
  -->
  <!-- these are the user-defined families for Basque. 
  -->
  <family indexRel="Restr" pos="Affix" closed="true" name="rel">
    <entry name="primary">
      <complexcat>
        <atomcat type="n">
          <fs id="0">
            <feat attr="index">
              <lf>
                <nomvar name="X"/>
              </lf>
            </feat>
          </fs>
        </atomcat>
        <slash dir="/" mode="*"/>
        <atomcat type="n">
          <fs id="0">
            <feat attr="index">
              <lf>
                <nomvar name="X"/>
              </lf>
            </feat>
          </fs>
        </atomcat>
        <slash dir="\" mode="*"/>
        <complexcat>
          <atomcat type="s">
            <fs id="1">
              <feat attr="index">
                <lf>
                  <nomvar name="E"/>
                </lf>
              </feat>
            </fs>
          </atomcat>
          <slash dir="\"/>
          <atomcat type="np">
            <!-- no structure sharing with fs 0; this aint HPSG-->
            <fs id="2">
              <feat attr="index">
                <lf>
                  <nomvar name="X"/>
                </lf>
              </feat>
            </fs>
          </atomcat>
        </complexcat>
        <lf>
          <satop nomvar="X">
            <diamond mode="Restr">
              <nomvar name="E"/>
            </diamond>
          </satop>
        </lf>
      </complexcat>
    </entry>
    <member stem="n"/>
  </family>
  <family pos="Affix" closed="true" name="case">
    <entry name="primary">
      <complexcat>
        <atomcat type="np">
          <fs id="0">
            <feat attr="person" val="3"/>
            <feat attr="index">
              <lf>
                <nomvar name="X"/>
              </lf>
            </feat>
          </fs>
        </atomcat>
        <slash dir="\" mode="*"/>
        <atomcat type="n">
          <fs id="1">
            <feat attr="index">
              <lf>
                <nomvar name="X"/>
              </lf>
            </feat>
          </fs>
        </atomcat>
        <lf>
          <satop nomvar="X">
            <diamond mode="Det">
              <nomvar name="D"/>
              <prop name="[*DEFAULT*]"/>
            </diamond>
          </satop>
        </lf>
      </complexcat>
    </entry>
    <member stem="a"/>
    <member stem="ak"/>
    <member stem="ri"/>
  </family>
  <family pos="N" closed="true" name="noun">
    <entry name="primary">
      <atomcat type="n">
        <fs id="0">
          <feat attr="person" val="3"/>
          <feat attr="num">
            <featvar name="NUM"/>
          </feat>
          <feat attr="index">
            <lf>
              <nomvar name="X"/>
            </lf>
          </feat>
        </fs>
        <lf>
          <satop nomvar="X">
            <prop name="[*DEFAULT*]"/>
          </satop>
        </lf>
      </atomcat>
    </entry>
    <member stem="gizon" pred="man"/>
    <member stem="eskola" pred="school"/>
    <member stem="seme" pred="son"/>
    <member stem="klase" pred="class"/>
    <member stem="emakume" pred="woman"/>
    <member stem="liburu" pred="book"/>
    <member stem="aita" pred="father"/>
    <member stem="ama" pred="mother"/>
    <member stem="kafe" pred="coffee"/>
  </family>
  <family pos="NP" closed="true" name="NP-case">
    <entry name="primary">
      <atomcat type="np">
        <fs id="0">
          <feat attr="num">
            <featvar name="NUM"/>
          </feat>
          <feat attr="index">
            <lf>
              <nomvar name="X"/>
            </lf>
          </feat>
        </fs>
        <lf>
          <satop nomvar="X">
            <prop name="[*DEFAULT*]"/>
          </satop>
        </lf>
      </atomcat>
    </entry>
    <member stem="kafe" pred="coffee"/>
    <member stem="aita" pred="father"/>
    <member stem="ama" pred="mother"/>
    <member stem="emakume" pred="woman"/>
    <member stem="sagarra" pred="apples"/>
    <member stem="liburu" pred="book"/>
    <member stem="gizon" pred="man"/>
  </family>
  <family pos="NNP" closed="true" name="pronoun">
    <entry name="primary">
      <atomcat type="np">
        <fs id="0">
          <feat attr="num">
            <featvar name="NUM"/>
          </feat>
          <feat attr="index">
            <lf>
              <nomvar name="X"/>
            </lf>
          </feat>
        </fs>
        <lf>
          <satop nomvar="X">
            <prop name="[*DEFAULT*]"/>
          </satop>
        </lf>
      </atomcat>
    </entry>
    <member stem="ni" pred="i"/>
  </family>
  <family closed="true" pos="V" name="AUX-intransitive">
    <entry name="primary">
      <complexcat>
        <atomcat type="s">
          <fs inheritsFrom="0">
            <feat attr="vform" val="fin"/>
            <feat attr="index">
              <lf>
                <nomvar name="E"/>
              </lf>
            </feat>
          </fs>
        </atomcat>
        <slash dir="\"/>
        <atomcat type="np">
          <fs id="1">
            <feat attr="index">
              <lf>
                <nomvar name="X"/>
              </lf>
            </feat>
          </fs>
        </atomcat>
        <slash dir="\" mode="*"/>
        <complexcat>
          <atomcat type="s">
            <fs id="0">
              <feat attr="vform" val="non-fin"/>
              <feat attr="index">
                <lf>
                  <nomvar name="E"/>
                </lf>
              </feat>
            </fs>
          </atomcat>
          <slash dir="\"/>
          <atomcat type="np">
            <fs id="1">
              <feat attr="index">
                <lf>
                  <nomvar name="X"/>
                </lf>
              </feat>
            </fs>
          </atomcat>
        </complexcat>
        <lf>
          <satop nomvar="P">
            <prop name="[*DEFAULT*]"/>
            <diamond mode="Asp">
              <nomvar name="E"/>
            </diamond>
          </satop>
        </lf>
      </complexcat>
    </entry>
    <member stem="dut1" pred="have"/>
    <member stem="zen1" pred="have"/>
    <member stem="dira1" pred="have"/>
  </family>
  <family closed="true" pos="V" name="AUX-transitive">
    <entry name="primary">
      <complexcat>
        <atomcat type="s">
          <fs inheritsFrom="0">
            <feat attr="vform" val="fin"/>
            <feat attr="index">
              <lf>
                <nomvar name="E"/>
              </lf>
            </feat>
          </fs>
        </atomcat>
        <setarg>
          <slash dir="\"/>
          <atomcat type="np">
            <fs id="1">
              <feat attr="index">
                <lf>
                  <nomvar name="X"/>
                </lf>
              </feat>
            </fs>
          </atomcat>
          <slash dir="\"/>
          <atomcat type="np">
            <fs id="2">
              <feat attr="index">
                <lf>
                  <nomvar name="X2"/>
                </lf>
              </feat>
            </fs>
          </atomcat>
        </setarg>
        <slash dir="\" mode="*"/>
        <complexcat>
          <atomcat type="s">
            <fs id="0">
              <feat attr="vform" val="non-fin"/>
              <feat attr="index">
                <lf>
                  <nomvar name="E"/>
                </lf>
              </feat>
            </fs>
          </atomcat>
          <slash dir="\"/>
          <atomcat type="np">
            <fs id="1">
              <feat attr="index">
                <lf>
                  <nomvar name="X"/>
                  <!-- NB. 'semantic' behaviour of AUX -->
                </lf>
              </feat>
            </fs>
          </atomcat>
          <slash dir="\"/>
          <atomcat type="np">
            <fs id="2">
              <feat attr="index">
                <lf>
                  <nomvar name="X2"/>
                </lf>
              </feat>
            </fs>
          </atomcat>
        </complexcat>
        <lf>
          <satop nomvar="P">
            <prop name="[*DEFAULT*]"/>
            <diamond mode="Asp">
              <nomvar name="E"/>
            </diamond>
          </satop>
        </lf>
      </complexcat>
    </entry>
    <member stem="dut2" pred="have"/>
    <member stem="nau" pred="have"/>
    <member stem="zuen1" pred="have"/>
    <member stem="ditu1" pred="have"/>
  </family>
  <family closed="true" pos="V" name="AUX-ditransitive">
    <entry name="primary">
      <complexcat>
        <atomcat type="s">
          <fs inheritsFrom="0">
            <feat attr="vform" val="fin"/>
            <feat attr="index">
              <lf>
                <nomvar name="E"/>
              </lf>
            </feat>
          </fs>
        </atomcat>
        <setarg>
          <slash dir="\"/>
          <atomcat type="np">
            <fs id="1">
              <feat attr="index">
                <lf>
                  <nomvar name="X"/>
                </lf>
              </feat>
            </fs>
          </atomcat>
          <slash dir="\"/>
          <atomcat type="np">
            <fs id="2">
              <feat attr="index">
                <lf>
                  <nomvar name="X2"/>
                </lf>
              </feat>
            </fs>
          </atomcat>
          <slash dir="\"/>
          <atomcat type="np">
            <fs id="3">
              <feat attr="index">
                <lf>
                  <nomvar name="X3"/>
                </lf>
              </feat>
            </fs>
          </atomcat>
        </setarg>
        <slash dir="\" mode="*"/>
        <complexcat>
          <atomcat type="s">
            <fs id="0">
              <feat attr="vform" val="non-fin"/>
              <feat attr="index">
                <lf>
                  <nomvar name="E"/>
                </lf>
              </feat>
            </fs>
          </atomcat>
          <slash dir="\"/>
          <atomcat type="np">
            <fs id="1">
              <feat attr="index">
                <lf>
                  <nomvar name="X"/>
                  <!-- NB 'semantic behaviour of AUX -->
                </lf>
              </feat>
            </fs>
          </atomcat>
          <slash dir="\"/>
          <atomcat type="np">
            <fs id="2">
              <feat attr="index">
                <lf>
                  <nomvar name="X2"/>
                </lf>
              </feat>
            </fs>
          </atomcat>
          <slash dir="\"/>
          <atomcat type="np">
            <fs id="3">
              <feat attr="index">
                <lf>
                  <nomvar name="X3"/>
                </lf>
              </feat>
            </fs>
          </atomcat>
        </complexcat>
        <lf>
          <satop nomvar="P">
            <prop name="[*DEFAULT*]"/>
            <diamond mode="Asp">
              <nomvar name="E"/>
            </diamond>
          </satop>
        </lf>
      </complexcat>
    </entry>
    <member stem="dio" pred="have"/>
  </family>
  <family closed="true" pos="V" name="DV">
    <entry name="primary">
      <complexcat>
        <atomcat type="s">
          <fs id="0">
            <feat attr="index">
              <lf>
                <nomvar name="E"/>
              </lf>
            </feat>
          </fs>
        </atomcat>
        <setarg>
          <slash dir="\"/>
          <atomcat type="np">
            <fs id="1">
              <feat attr="case" val="a-case"/>
              <feat attr="index">
                <lf>
                  <nomvar name="X1:1"/>
                </lf>
              </feat>
            </fs>
          </atomcat>
          <slash dir="\"/>
          <atomcat type="np">
            <fs id="2">
              <feat attr="case" val="p-case"/>
              <feat attr="index">
                <lf>
                  <nomvar name="X2:2"/>
                </lf>
              </feat>
            </fs>
          </atomcat>
          <slash dir="\"/>
          <atomcat type="np">
            <fs id="3">
              <feat attr="case" val="dat"/>
              <feat attr="index">
                <lf>
                  <nomvar name="X3:3"/>
                </lf>
              </feat>
            </fs>
          </atomcat>
        </setarg>
        <lf>
          <satop nomvar="E">
            <prop name="[*DEFAULT*]"/>
            <diamond mode="Arg1">
              <nomvar name="X1:1"/>
            </diamond>
            <diamond mode="Arg2">
              <nomvar name="X2:2"/>
            </diamond>
            <diamond mode="Arg3">
              <nomvar name="X3:3"/>
            </diamond>
          </satop>
        </lf>
      </complexcat>
    </entry>
    <member stem="eman" pred="give"/>
  </family>
  <family closed="true" pos="Conj" name="Conj">
    <entry name="sentential">
      <complexcat>
        <atomcat type="s">
          <fs inheritsFrom="1">
            <feat attr="index">
              <lf>
                <nomvar name="S0"/>
              </lf>
            </feat>
          </fs>
        </atomcat>
        <slash dir="/" mode="*"/>
        <atomcat type="s">
          <fs inheritsFrom="1">
            <feat attr="index">
              <lf>
                <nomvar name="S1"/>
              </lf>
            </feat>
          </fs>
        </atomcat>
        <slash dir="\" mode="*"/>
        <atomcat type="s">
          <fs id="1">
            <feat attr="index">
              <lf>
                <nomvar name="S2"/>
              </lf>
            </feat>
          </fs>
        </atomcat>
        <lf>
          <satop nomvar="S0">
            <prop name="[*DEFAULT*]"/>
            <diamond mode="List">
              <nomvar name="S1"/>
              <diamond mode="Coord">
                <nomvar name="S2"/>
              </diamond>
            </diamond>
          </satop>
        </lf>
      </complexcat>
    </entry>
    <entry name="1-VP">
      <complexcat>
        <atomcat type="s">
          <fs inheritsFrom="1">
            <feat attr="index">
              <lf>
                <nomvar name="S0"/>
              </lf>
            </feat>
          </fs>
        </atomcat>
        <slash dir="\"/>
        <atomcat type="np">
          <fs>
            <feat attr="case">
              <featvar name="Case1"/>
            </feat>
            <feat attr="index">
              <lf>
                <nomvar name="X"/>
              </lf>
            </feat>
          </fs>
        </atomcat>
        <slash dir="\" mode="*"/>
        <complexcat>
          <atomcat type="s">
            <fs inheritsFrom="1">
              <feat attr="index">
                <lf>
                  <nomvar name="S1"/>
                </lf>
              </feat>
            </fs>
          </atomcat>
          <slash dir="\"/>
          <atomcat type="np">
            <fs>
              <feat attr="case">
                <featvar name="Case1"/>
              </feat>
              <feat attr="index">
                <lf>
                  <nomvar name="X"/>
                </lf>
              </feat>
            </fs>
          </atomcat>
        </complexcat>
        <slash dir="/" mode="*"/>
        <complexcat>
          <atomcat type="s">
            <fs id="1">
              <feat attr="index">
                <lf>
                  <nomvar name="S2"/>
                </lf>
              </feat>
            </fs>
          </atomcat>
          <slash dir="\"/>
          <atomcat type="np">
            <fs>
              <feat attr="case">
                <featvar name="Case2"/>
              </feat>
              <feat attr="index">
                <lf>
                  <nomvar name="X"/>
                </lf>
              </feat>
            </fs>
          </atomcat>
        </complexcat>
        <lf>
          <satop nomvar="S0">
            <prop name="[*DEFAULT*]"/>
            <diamond mode="List">
              <nomvar name="S1"/>
              <diamond mode="Coord">
                <nomvar name="S2"/>
              </diamond>
            </diamond>
          </satop>
        </lf>
      </complexcat>
    </entry>
    <member stem="eta" pred="and"/>
  </family>
  <family closed="true" pos="Affix" name="adjunct-case">
    <entry name="primary">
      <complexcat>
        <atomcat type="s">
          <fs id="0">
            <feat attr="index">
              <lf>
                <nomvar name="E"/>
              </lf>
            </feat>
          </fs>
        </atomcat>
        <slash/>
        <dollar name="1"/>
        <slash dir="/"/>
        <complexcat>
          <atomcat type="s">
            <fs id="0">
              <feat attr="index">
                <lf>
                  <nomvar name="E"/>
                </lf>
              </feat>
            </fs>
          </atomcat>
          <slash/>
          <dollar name="1"/>
        </complexcat>
        <slash dir="\" mode="*"/>
        <atomcat type="n">
          <fs id="2">
            <feat attr="index">
              <lf>
                <nomvar name="Y"/>
              </lf>
            </feat>
          </fs>
        </atomcat>
        <lf>
          <satop nomvar="P">
            <prop name="[*DEFAULT*]"/>
            <diamond mode="Pred">
              <nomvar name="E"/>
              <diamond mode="Mod">
                <nomvar name="Y"/>
              </diamond>
            </diamond>
          </satop>
        </lf>
      </complexcat>
    </entry>
    <member stem="n" pred="at"/>
    <member stem="ra" pred="to"/>
  </family>
</ccg-lexicon>
