<?xml version="1.0" encoding="UTF-8"?>
<!-- 
      - This file is generated by lexicon-skeleton.xsl to set up
          accusativity/ergativity parameter for IV and TV primary families
          and control primary families.

          NB: pre-CCG categories of lexicon-skeleton.xml are mapped to
              CCG categories in this file. From now on, it's all CCG

    Suggestions to start-up lexicon development:

      1) Copy this file to lexicon-base.xml to avoid losing your changes
         to it (remember, this file is auto-generated at the start)
      2) Edit lexicon-base.xml to modify the preset families and to add your 
          own families as needed (merging the entries of same family is
          left to you)
      3) Use the build facility of openCCG to build
          the lexicon.xml, morph.xml and rules.xml files needed by the system.
  -->
<!-- Additional families by Cem Bozsahin, 6/2003 -->
<!--

      *** Families derived from language parameters ***

   Includes primary entries for IV, TV, TV-control1, TV-control2, IV-control1
   
  -->
<ccg-lexicon name="Dyirbal" xmlns:xsi="http://www.w3.org/2001/XMLSchema-instance" xsi:noNamespaceSchemaLocation="../lexicon.xsd">

  <family closed="true" pos="V" name="IV">
    <entry name="primary">
      <complexcat>
        <atomcat type="s">
          <fs id="0">
            <feat attr="index">
              <lf>
                <nomvar name="E"/>
              </lf>
            </feat>
          </fs>
        </atomcat>
        <slash dir="\"/>
        <atomcat type="np">
          <fs id="1">
            <feat attr="case" val="s-case"/>
            <feat attr="index">
              <lf>
                <nomvar name="X1"/>
              </lf>
            </feat>
          </fs>
        </atomcat>
        <lf>
          <satop nomvar="E">
            <prop name="[*DEFAULT*]"/>
            <diamond mode="Arg1">
              <nomvar name="X1"/>
            </diamond>
          </satop>
        </lf>
      </complexcat>
    </entry>
  </family>

  <family closed="true" pos="V" name="TV">
    <entry name="primary">
      <complexcat>
        <atomcat type="s">
          <fs id="0">
            <feat attr="index">
              <lf>
                <nomvar name="E"/>
              </lf>
            </feat>
          </fs>
        </atomcat>
        <setarg>
          <slash dir="\"/>
          <atomcat type="np">
            <fs id="1">
              <feat attr="case" val="a-case"/>
              <feat attr="index">
                <lf>
                  <nomvar name="X1"/>
                </lf>
              </feat>
            </fs>
          </atomcat>
          <slash dir="\"/>
          <atomcat type="np">
            <fs id="2">
              <feat attr="case" val="p-case"/>
              <feat attr="index">
                <lf>
                  <nomvar name="X2"/>
                </lf>
              </feat>
            </fs>
          </atomcat>
        </setarg>
        <lf>
          <satop nomvar="E">
            <prop name="[*DEFAULT*]"/>
            <diamond mode="Arg1">
              <nomvar name="X1"/>
            </diamond>
            <diamond mode="Arg2">
              <nomvar name="X2"/>
            </diamond>
          </satop>
        </lf>
      </complexcat>
    </entry>
  </family>
  <family closed="true" pos="V" name="TV-control2">
    <entry name="primary">
      <complexcat>
        <atomcat type="s">
          <fs id="0">
            <feat attr="index">
              <lf>
                <nomvar name="E"/>
              </lf>
            </feat>
          </fs>
        </atomcat>
        <setarg>
          <slash dir="\"/>
          <atomcat type="np">
            <fs id="1">
              <feat attr="case" val="a-case"/>
              <feat attr="index">
                <lf>
                  <nomvar name="X1"/>
                </lf>
              </feat>
            </fs>
          </atomcat>
          <slash dir="|"/>
          <complexcat>
                  <!--NB: Word order and directionality of embedded clause's |(S|NP) 
type is an 'educated guess' from the syntactic type of TV. Change them
accordingly 
  -->
            <atomcat type="s">
              <fs id="3">
                <feat val="non-fin" attr="vform"/>
                <feat attr="index">
                  <lf>
                    <nomvar name="E2"/>
                  </lf>
                </feat>
              </fs>
            </atomcat>
            <slash dir="|"/>
            <atomcat type="np">
              <fs id="4">
                 <feat attr="case" val="subject-case"/>
                <feat attr="index">
                  <lf>
                    <nomvar name="X2"/>
                  </lf>
                           <!--NB: Index is same as Arg2's 
  -->
                </feat>
              </fs>
            </atomcat>
          </complexcat>
          <slash dir="\"/>
          <atomcat type="np">
            <fs id="2">
              <feat attr="case" val="p-case"/>
              <feat attr="index">
                <lf>
                  <nomvar name="X2"/>
                </lf>
              </feat>
            </fs>
          </atomcat>
        </setarg>
        <lf>
          <satop nomvar="E">
            <prop name="[*DEFAULT*]"/>
            <diamond mode="Arg1">
              <nomvar name="X1"/>
            </diamond>
            <diamond mode="Arg2">
              <nomvar name="X2"/>
            </diamond>
            <diamond mode="Arg3">
              <nomvar name="E2"/>
                     <!--NB: Argument is the PAS of the embedded S|NP  (cf. E2 above)
-->
            </diamond>
          </satop>
        </lf>
      </complexcat>
    </entry>
  </family>
  <family closed="true" pos="V" name="TV-control1">
    <entry name="primary">
      <complexcat>
        <atomcat type="s">
          <fs id="0">
            <feat attr="index">
              <lf>
                <nomvar name="E"/>
              </lf>
            </feat>
          </fs>
        </atomcat>
        <setarg>
          <slash dir="\"/>
          <atomcat type="np">
            <fs id="1">
              <feat attr="case" val="a-case"/>
              <feat attr="index">
                <lf>
                  <nomvar name="X1"/>
                </lf>
              </feat>
            </fs>
          </atomcat>
          <slash dir="|"/>
          <complexcat>
                  <!--NB: Word order and directionality of embedded clause's 
|(S|NP) type is an 'educated guess' from the syntactic type of TV. 
Change them accordingly.
  -->
            <atomcat type="s">
              <fs id="3">
                <feat val="non-fin" attr="vform"/>
                <feat attr="index">
                  <lf>
                    <nomvar name="E2"/>
                  </lf>
                </feat>
              </fs>
            </atomcat>
            <slash dir="|"/>
            <atomcat type="np">
              <fs id="4">
                <feat attr="case" val="subject-case"/>
                <feat attr="index">
                  <lf>
                    <nomvar name="X1"/>
                  </lf>
                           <!--NB: Index is same as Arg1's 
  -->
                </feat>
              </fs>
            </atomcat>
          </complexcat>
          <slash dir="\"/>
          <atomcat type="np">
            <fs id="2">
              <feat attr="case" val="p-case"/>
              <feat attr="index">
                <lf>
                  <nomvar name="X2"/>
                </lf>
              </feat>
            </fs>
          </atomcat>
        </setarg>
        <lf>
          <satop nomvar="E">
            <prop name="[*DEFAULT*]"/>
            <diamond mode="Arg1">
              <nomvar name="X1"/>
            </diamond>
            <diamond mode="Arg2">
              <nomvar name="X2"/>
            </diamond>
            <diamond mode="Arg3">
              <nomvar name="E2"/>
                     <!--NB: Argument is the PAS of the embedded S|NP  (cf. E2 above)
-->
            </diamond>
          </satop>
        </lf>
      </complexcat>
    </entry>
  </family>
  <family closed="true" pos="V" name="IV-control1">
    <entry name="primary">
      <complexcat>
        <atomcat type="s">
          <fs id="0">
            <feat attr="index">
              <lf>
                <nomvar name="E"/>
              </lf>
            </feat>
          </fs>
        </atomcat>
        <setarg>
          <slash dir="\"/>
          <atomcat type="np">
            <fs id="1">
              <feat attr="case" val="s-case"/>
              <feat attr="index">
                <lf>
                  <nomvar name="X1"/>
                </lf>
              </feat>
            </fs>
          </atomcat>
          <slash dir="|"/>
          <complexcat>
                  <!--NB: Word order and directionality of embedded clause's 
|(S|NP) type is an 'educated guess' from the syntactic type of TV. 
Change them accordingly.
  -->
            <atomcat type="s">
              <fs id="3">
                <feat val="non-fin" attr="vform"/>
                <feat attr="index">
                  <lf>
                    <nomvar name="E2"/>
                  </lf>
                </feat>
              </fs>
            </atomcat>
            <slash dir="|"/>
            <atomcat type="np">
              <fs id="4">
              <feat attr="case" val="subject-case"/>
               <feat attr="index">
                  <lf>
                    <nomvar name="X1"/>
                  </lf>
                           <!--NB: Index is same as Arg1's 
  -->
                </feat>
              </fs>
            </atomcat>
          </complexcat>
        </setarg>
        <lf>
          <satop nomvar="E">
            <prop name="[*DEFAULT*]"/>
            <diamond mode="Arg1">
              <nomvar name="X1"/>
            </diamond>
            <diamond mode="Arg2">
              <nomvar name="E2"/>
                     <!--NB: Argument is the PAS of the embedded S|NP  (cf. E2 above)
-->
            </diamond>
          </satop>
        </lf>
      </complexcat>
    </entry>
  </family>
   <!--

    *** End of derived families ***
 
        Add new families here, and merge the new entries for preset
         families as needed (e.g., you may add an entry to TV family
         for pro-dropping the subject etc.)
  -->

<!-- these are the user-defined families for Dyirbal.
  -->

  <family indexRel="*noSem*" pos="Affix" closed="true" name="rel-case">
    <entry name="primary">
      <complexcat>
        <atomcat type="np">
          <fs inheritsFrom="0">
            <feat attr="index">
              <lf>
                <nomvar name="Y"/>
              </lf>
            </feat>
          </fs>
        </atomcat>
        <slash dir="\"/>
        <atomcat type="np">
          <fs inheritsFrom="1">
            <feat attr="case" val="a-case"/>
            <feat attr="index">
              <lf>
                <nomvar name="X"/>
              </lf>
            </feat>
          </fs>
        </atomcat>
        <slash dir="\" mode="*"/>
        <complexcat>
          <atomcat type="n">
            <fs id="0">
              <feat attr="index">
                <lf>
                  <nomvar name="Y"/>
                </lf>
              </feat>
            </fs>
          </atomcat>
          <slash dir="\"/>
          <atomcat type="n">
            <fs id="1">
              <feat attr="case" val="subject-case"/>
              <feat attr="index">
                <lf>
                  <nomvar name="X"/>
                </lf>
              </feat>
            </fs>
          </atomcat>
        </complexcat>
<!--
      <lf>
        <satop nomvar="Y">
          <prop name="[*DEFAULT*]"/>
          <diamond mode="Spec">
            <nomvar name="X"/>
          </diamond>
        </satop>
      </lf>
-->
      </complexcat>
    </entry>
  </family>

  <family indexRel="Restr" pos="Affix" closed="true" name="rel">
    <entry name="primary">
      <complexcat>
        <atomcat type="n">
          <fs id="0">
            <feat attr="index">
              <lf>
                <nomvar name="X"/>
              </lf>
            </feat>
          </fs>
        </atomcat>
        <slash dir="\"/>
        <atomcat type="n">
          <fs id="0">
            <feat attr="index">
              <lf>
                <nomvar name="X"/>
              </lf>
            </feat>
          </fs>
        </atomcat>
        <slash dir="\" mode="*"/>
        <complexcat>
          <atomcat type="s">
            <fs id="1">
              <feat attr="index">
                <lf>
                  <nomvar name="E"/>
                </lf>
              </feat>
            </fs>
          </atomcat>
          <slash dir="\"/>
          <atomcat type="np">
<!-- no structure sharing with fs 0; this aint HPSG-->
            <fs id="2">
              <feat attr="case" val="subject-case"/>
              <feat attr="index">
                <lf>
                  <nomvar name="X"/>
                </lf>
              </feat>
            </fs>
          </atomcat>
        </complexcat>
        <lf>
          <satop nomvar="X">
            <diamond mode="Restr">
              <nomvar name="E"/>
            </diamond>
          </satop>
        </lf>
      </complexcat>
    </entry>
  </family>

  <family closed="true" pos="Affix" name="voice">
    <entry name="anti-passive">
      <complexcat>
        <atomcat type="s">
          <fs inheritsFrom="0">
            <feat attr="index">
              <lf>
                <nomvar name="P"/>
              </lf>
            </feat>
          </fs>
        </atomcat>
        <slash dir="\"/>
        <atomcat type="np">
          <fs inheritsFrom="2">
            <feat attr="case" val="subject-case"/>
            <feat attr="index">
              <lf>
                <nomvar name="X"/>
              </lf>
            </feat>
          </fs>
        </atomcat>
        <slash dir="\" mode="*"/>
        <complexcat>
          <atomcat type="s">
            <fs id="0">
              <feat attr="index">
                <lf>
                  <nomvar name="E"/>
                </lf>
              </feat>
            </fs>
          </atomcat>
          <slash dir="\"/>
          <atomcat type="np">
            <fs id="1">
              <feat attr="case" val="a-case"/>
              <feat attr="index">
                <lf>
                  <nomvar name="X"/>
                </lf>
              </feat>
            </fs>
          </atomcat>
          <slash dir="\"/>
          <atomcat type="np">
            <fs id="2">
              <feat attr="case" val="subject-case"/>
              <feat attr="index">
                <lf>
                  <nomvar name="X2"/>
                </lf>
              </feat>
            </fs>
          </atomcat>
        </complexcat>
        <lf>
          <satop nomvar="P">
            <prop name="[*DEFAULT*]"/>
            <diamond mode="Pred">
              <nomvar name="E"/>
            </diamond>
            <diamond mode="Arg1">
              <nomvar name="X"/>
            </diamond>
          </satop>
        </lf>
      </complexcat>
    </entry>
  </family>

  <family pos="Affix" closed="true" name="case">
    <entry name="primary">
      <complexcat>
        <atomcat type="np">
          <fs id="0">
            <feat attr="person" val="3"/>
            <feat attr="index">
              <lf>
                <nomvar name="X"/>
              </lf>
            </feat>
          </fs>
        </atomcat>
        <slash dir="\" mode="*"/>
        <atomcat type="np">
          <fs id="1">
            <feat attr="person" val="3"/>
            <feat attr="index">
              <lf>
                <nomvar name="X"/>
              </lf>
            </feat>
          </fs>
        </atomcat>
        <lf>
          <satop nomvar="X">
            <diamond mode="Spec">
              <nomvar name="D"/>
              <prop name="[*DEFAULT*]"/>
            </diamond>
          </satop>
        </lf>
      </complexcat>
    </entry>
  </family>

  <family closed="true" pos="Affix" name="adjunct-case">
    <entry name="primary">
      <complexcat>
        <atomcat type="s">
          <fs id="0">
            <feat attr="index">
              <lf>
                <nomvar name="E"/>
              </lf>
            </feat>
          </fs>
        </atomcat>
        <slash/>
        <dollar name="1"/>
        <slash dir="|"/>
        <complexcat>
          <atomcat type="s">
            <fs id="0">
              <feat attr="index">
                <lf>
                  <nomvar name="E"/>
                </lf>
              </feat>
            </fs>
          </atomcat>
          <slash/>
          <dollar name="1"/>
        </complexcat>
        <slash dir="\" mode="*"/>
        <atomcat type="np">
          <fs id="2">
            <feat attr="index">
              <lf>
                <nomvar name="Y"/>
              </lf>
            </feat>
          </fs>
        </atomcat>
        <lf>
          <satop nomvar="P">
            <prop name="[*DEFAULT*]"/>
            <diamond mode="Pred">
              <nomvar name="E"/>
              <diamond mode="Mod">
                <nomvar name="Y"/>
              </diamond>
            </diamond>
          </satop>
        </lf>
      </complexcat>
    </entry>
  </family>

  <family pos="NP" closed="true" name="Noun">
    <entry name="primary">
      <atomcat type="np">
        <fs id="0">
          <feat attr="num">
            <featvar name="NUM"/>
          </feat>
          <feat attr="index">
            <lf>
              <nomvar name="X"/>
            </lf>
          </feat>
        </fs>
        <lf>
          <satop nomvar="X">
            <prop name="[*DEFAULT*]"/>
          </satop>
        </lf>
      </atomcat>
    </entry>
    <entry name="bare">
      <atomcat type="n">
        <fs id="1">
          <feat attr="num">
            <featvar name="NUM"/>
          </feat>
          <feat attr="index">
            <lf>
              <nomvar name="X"/>
            </lf>
          </feat>
        </fs>
        <lf>
          <satop nomvar="X">
            <prop name="[*DEFAULT*]"/>
          </satop>
        </lf>
      </atomcat>
    </entry>
  </family>

  <family pos="NNP" closed="true" name="pronoun">
    <entry name="primary">
      <atomcat type="np">
        <fs id="0">
          <feat attr="num">
            <featvar name="NUM"/>
          </feat>
          <feat attr="index">
            <lf>
              <nomvar name="X"/>
            </lf>
          </feat>
        </fs>
        <lf>
          <satop nomvar="X">
            <prop name="[*DEFAULT*]"/>
          </satop>
        </lf>
      </atomcat>
    </entry>
  </family>

  <family pos="NP" closed="true" name="N-class">
    <entry name="primary">
      <complexcat>
        <atomcat type="np">
          <fs id="0">
            <feat attr="person" val="3"/>
            <feat attr="index">
              <lf>
                <nomvar name="X"/>
              </lf>
            </feat>
          </fs>
        </atomcat>
        <slash dir="/" mode="*"/>
        <atomcat type="n">
          <fs id="0">
            <feat attr="index">
              <lf>
                <nomvar name="X"/>
              </lf>
            </feat>
          </fs>
        </atomcat>
      </complexcat>
    </entry>
    <entry name="NP-like">
      <atomcat type="np">
        <fs id="0">
          <feat attr="person" val="3"/>
          <feat attr="num">
            <featvar name="NUM"/>
          </feat>
          <feat attr="index">
            <lf>
              <nomvar name="X"/>
            </lf>
          </feat>
        </fs>
      </atomcat>
    </entry>
  </family>

  <family closed="true" pos="Conj" name="Conj">
    <entry name="sentential">
      <complexcat>
        <atomcat type="s">
          <fs inheritsFrom="1">
            <feat attr="index">
              <lf>
                <nomvar name="S0"/>
              </lf>
            </feat>
          </fs>
        </atomcat>
        <slash/>
        <dollar name="1"/>
        <slash dir="/" mode="*"/>
        <complexcat>
          <atomcat type="s">
            <fs inheritsFrom="1">
              <feat attr="index">
                <lf>
                  <nomvar name="S1"/>
                </lf>
              </feat>
            </fs>
          </atomcat>
          <slash/>
          <dollar name="1"/>
        </complexcat>
        <slash dir="\" mode="*"/>
        <complexcat>
          <atomcat type="s">
            <fs id="1">
              <feat attr="index">
                <lf>
                  <nomvar name="S2"/>
                </lf>
              </feat>
            </fs>
          </atomcat>
          <slash/>
          <dollar name="1"/>
        </complexcat>
        <lf>
          <satop nomvar="S0">
            <prop name="[*DEFAULT*]"/>
            <diamond mode="List">
              <nomvar name="S1"/>
              <diamond mode="Coord">
                <nomvar name="S2"/>
              </diamond>
            </diamond>
          </satop>
        </lf>
      </complexcat>
    </entry>
  </family>

</ccg-lexicon>
